LICENSE
MANIFEST.in
README.md
requirements.txt
setup.py
rule_evaluator/__init__.py
rule_evaluator/rule_evaluator.py
rule_evaluator.egg-info/PKG-INFO
rule_evaluator.egg-info/SOURCES.txt
rule_evaluator.egg-info/dependency_links.txt
rule_evaluator.egg-info/requires.txt
rule_evaluator.egg-info/top_level.txt