Metadata-Version: 2.1
Name: rule-evaluator
Version: 2024.8.14.post1
Summary: Lightweight Python-based nested rule evaluator
Home-page: https://github.com/jolespin/rule_evaluator
Author: Josh L. Espinoza
License: GPLv3
Requires-Python: >=3.7
License-File: LICENSE
Requires-Dist: parsimonious
